testdummypackage/__init__.py
testdummypackage/add.py
testdummypackage-0.1.1.dist-info/METADATA
testdummypackage-0.1.1.dist-info/WHEEL
testdummypackage-0.1.1.dist-info/RECORD
